[{
  "_id": 1,
  "videoType": "Public",
  "createdAt": {
    "$date": "2022-01-03T11:24:13.303Z"
  },
  "updatedAt": {
    "$date": "2022-01-03T11:24:13.303Z"
  },
  "__v": 0
},{
  "_id": 2,
  "videoType": "Private",
  "createdAt": {
    "$date": "2022-01-03T11:24:19.670Z"
  },
  "updatedAt": {
    "$date": "2022-01-03T11:24:19.670Z"
  },
  "__v": 0
},{
  "_id": 3,
  "videoType": "Unlisted",
  "createdAt": {
    "$date": "2022-01-03T11:24:19.724Z"
  },
  "updatedAt": {
    "$date": "2022-01-03T11:24:19.724Z"
  },
  "__v": 0
}]